djangocms_simple_admin_style/__init__.py
djangocms_simple_admin_style/static/admin/img/icon-addlink.svg
djangocms_simple_admin_style/static/admin/img/icon-alert.svg
djangocms_simple_admin_style/static/admin/img/icon-changelink.svg
djangocms_simple_admin_style/static/admin/img/icon-deletelink.svg
djangocms_simple_admin_style/static/admin/img/icon-hidelink.svg
djangocms_simple_admin_style/static/admin/img/icon-no.svg
djangocms_simple_admin_style/static/admin/img/icon-unknown-alt.svg
djangocms_simple_admin_style/static/admin/img/icon-unknown.svg
djangocms_simple_admin_style/static/admin/img/icon-viewlink.svg
djangocms_simple_admin_style/static/admin/img/icon-yes.svg
djangocms_simple_admin_style/static/admin/img/search.svg
djangocms_simple_admin_style/static/djangocms_simple_admin_style/css/djangocms-simple-admin.min.css
djangocms_simple_admin_style/static/djangocms_simple_admin_style/js/update-notification.js
djangocms_simple_admin_style/templates/admin/base_site.html
djangocms_simple_admin_style/templates/admin/inc/cms_upgrade_notification.html
djangocms_simple_admin_style/templates/admin/inc/extrastyle.html
djangocms_simple_admin_style/templatetags/__init__.py
djangocms_simple_admin_style/templatetags/admin_style_tags.py
djangocms_simple_admin_style-2.0.0.dist-info/METADATA
djangocms_simple_admin_style-2.0.0.dist-info/WHEEL
djangocms_simple_admin_style-2.0.0.dist-info/licenses/LICENSE
djangocms_simple_admin_style-2.0.0.dist-info/RECORD
